db_api_server/__init__.py
db_api_server/__main__.py
db_api_server/server.py
prometheus_vcgencmd/__init__.py
prometheus_vcgencmd/__main__.py
prometheus_vcgencmd/prometheus_vcgencmd.py
prometheus_vcgencmd-1.0.0.dist-info/LICENSE
prometheus_vcgencmd-1.0.0.dist-info/METADATA
prometheus_vcgencmd-1.0.0.dist-info/WHEEL
prometheus_vcgencmd-1.0.0.dist-info/entry_points.txt
prometheus_vcgencmd-1.0.0.dist-info/top_level.txt
prometheus_vcgencmd-1.0.0.dist-info/RECORD
